{
  "name": "Victoria Maxwell",
  "age": 22,
  "address": {
    "street": "Serhav Boulevard",
    "city": "Rekwocara",
    "state": "NC",
    "zip": "98666"
  },
  "contact": {
    "phone": "(926) 207-5996",
    "servicePhone": "800482331"
  },
  "birthday": "1984-06-22T03:57:11.408Z",
  "ip": "106.213.141.97",
  "foo": "bar",
  "profile": {
    "about": "Buziha towmacut ziir amnufon wut gucdavkos tena moazoduz gidlo tak kormejhij awibeh kojimet eb ugeka mu para afaarvec. Vahfovgi od uzifocar ib elgub wid no gican dadad jizmacap livce woracvin dakgu ezuweina dosal ug. Boivito atalu naj tibedji rovo midde di veilwo iwupu nandiz ki edeikrad jafewmed af wolaloli fo. Gakal parikfa lemgima hol tukejwe majsaz kul na cumfuwece eseipulo rupel zatu. Biti bajun hafu roir inu lag loipawoj du uduciz om pepgo kuf nalodse.",
    "bio": "Fule himde wem fuco gidatogi ro utaluehe tihvusa ahu vosvu tah bef ni sujuw. Heb cocsot neda minusbe am gefono ja pekipuw nerrifno dotachom ge petjakges nosfub wurad bengadkiz si. Misodik dic fotuab izegiz jet pujdeow keziv sit nafworuhu fe zipa lihhulgoc gebmunzi nun. Busowu en olge lipraf dunlasu femimna we dija wuvsujzoh fa gub net sa nalaru modpuzkes ubuke. Peguje pik zumuhaki zaze sa wizouzo uh sakan sa uniunga sug vi nijfevhur or nolpac ga domjoiwe sicje. Fi zipra jefdal bor cegjeviw is fuvezo ati fefiwiho ponorunoc zusawme zizivuone bidobvol adhacge kovizig vidarlac unmi putwa. Vokhi afaji vetbup sorve tejgep dewic onouraw ecebav fo teclug adseb tezodbun."
  },
  "apiKey": "07047f52b487ed7a4635646bff8abe38f7d2e656907e01141c6476396e45f8e3",
  "currency": {
    "code": "SYP",
    "name": "Syria Pound"
  }
}